README.md
pymvngit/__init__.py
pymvngit/console.py
pymvngit/prettytable.py
pymvngit/pygit.py
pymvngit/pymvngit.py
pymvngit/tableargs.py
pymvngit/utils.py
pymvngit.egg-info/PKG-INFO
pymvngit.egg-info/SOURCES.txt
pymvngit.egg-info/dependency_links.txt
pymvngit.egg-info/entry_points.txt
pymvngit.egg-info/requires.txt
pymvngit.egg-info/top_level.txt
pymvngit-0.2.2.dist-info/METADATA
pymvngit-0.2.2.dist-info/WHEEL
pymvngit-0.2.2.dist-info/entry_points.txt
pymvngit-0.2.2.dist-info/top_level.txt
pymvngit-0.2.2.dist-info/RECORD
