Metadata-Version: 2.1
Name: pymvngit
Version: 0.2.2
Summary: Tool to manage a group of Git/Maven projects.
Home-page: UNKNOWN
Author: Ualter Otoni Pereira
Author-email: ualter.junior@gmail.com
License: MIT
Keywords: maven,git,tool,java,microservices,lerna
Platform: UNKNOWN
Classifier: Development Status :: 3 - Alpha
Classifier: License :: OSI Approved :: MIT License
Classifier: Programming Language :: Python :: 3
Classifier: Programming Language :: Python :: 3.7
Requires-Dist: Pygments
Requires-Dist: clipboard
Requires-Dist: gitpython
Requires-Dist: tinydb
